setup.py
alibabacloud_ha3engine_vector/__init__.py
alibabacloud_ha3engine_vector/client.py
alibabacloud_ha3engine_vector/models.py
alibabacloud_ha3engine_vector.egg-info/PKG-INFO
alibabacloud_ha3engine_vector.egg-info/SOURCES.txt
alibabacloud_ha3engine_vector.egg-info/dependency_links.txt
alibabacloud_ha3engine_vector.egg-info/requires.txt
alibabacloud_ha3engine_vector.egg-info/top_level.txt